message_rules/__init__.py
message_rules/message_rules.py
message_rules-1.1.0.dist-info/DESCRIPTION.rst
message_rules-1.1.0.dist-info/METADATA
message_rules-1.1.0.dist-info/RECORD
message_rules-1.1.0.dist-info/WHEEL
message_rules-1.1.0.dist-info/metadata.json
message_rules-1.1.0.dist-info/top_level.txt
