Metadata-Version: 2.0
Name: message-rules
Version: 1.1.0
Summary: Fast, simple message rules
Provides-Extra: dev
Requires-Dist: check-manifest; extra == 'dev'
Requires-Dist: message-rules; extra == 'dev'
Requires-Dist: message-transform; extra == 'dev'
Provides-Extra: test
Requires-Dist: message-rules; extra == 'test'
Requires-Dist: message-transform; extra == 'test'
Requires-Dist: pytest; extra == 'test'
Requires-Dist: sys; extra == 'test'
